rlnav/__init__.py
rlnav/utils.py
rlnav/ant_maze/__init__.py
rlnav/ant_maze/ant_maze_v0.py
rlnav/ant_maze/mujoco_model_utils.py
rlnav/ant_maze/maps/__init__.py
rlnav/ant_maze/maps/empty_room.py
rlnav/ant_maze/maps/empty_room_small.py
rlnav/ant_maze/maps/extreme_maze.py
rlnav/ant_maze/maps/four_rooms.py
rlnav/ant_maze/maps/hard_maze.py
rlnav/ant_maze/maps/maps_index.py
rlnav/ant_maze/maps/medium_maze.py
rlnav/ant_maze/maps/tile_type.py
rlnav/ant_maze/mujoco_files/__init__.py
rlnav/ant_maze/mujoco_files/xml_generator.py
rlnav/ant_maze/mujoco_files/common/__init__.py
rlnav/doom_maze/__init__.py
rlnav/doom_maze/doom_maze.py
rlnav/doom_maze/spectator.py
rlnav/doom_maze/wads_builder.py
rlnav/grid_world/__init__.py
rlnav/grid_world/grid_world_v0.py
rlnav/grid_world/maps/__init__.py
rlnav/grid_world/maps/empty_room.py
rlnav/grid_world/maps/extreme_maze.py
rlnav/grid_world/maps/four_rooms.py
rlnav/grid_world/maps/hard_maze.py
rlnav/grid_world/maps/medium_maze.py
rlnav/grid_world/utils/__init__.py
rlnav/grid_world/utils/images_fun.py
rlnav/maps/__init__.py
rlnav/maps/build_map.py
rlnav/maps/empty_room.py
rlnav/maps/empty_room_small.py
rlnav/maps/extreme_maze.py
rlnav/maps/four_rooms.py
rlnav/maps/hard_maze.py
rlnav/maps/maps_index.py
rlnav/maps/medium_maze.py
rlnav/maps/tile_type.py
rlnav/point_maze/__init__.py
rlnav/point_maze/maps_index.py
rlnav/point_maze/point_maze_v0.py
rlnav/point_maze/maps/__init__.py
rlnav/point_maze/maps/empty_room.py
rlnav/point_maze/maps/extreme_maze.py
rlnav/point_maze/maps/four_rooms.py
rlnav/point_maze/maps/hard_maze.py
rlnav/point_maze/maps/impossible_maze.py
rlnav/point_maze/maps/join_room_medium.py
rlnav/point_maze/maps/medium_maze.py
rlnav/point_maze/utils/__init__.py
rlnav/point_maze/utils/images_fun.py
rlnav/point_maze/utils/indexes.py
rlnav-1.4.15.dist-info/METADATA
rlnav-1.4.15.dist-info/WHEEL
rlnav-1.4.15.dist-info/top_level.txt
rlnav-1.4.15.dist-info/RECORD
