Metadata-Version: 2.4
Name: rlnav
Version: 1.4.15
Summary: Reinforcement Learning Navigation Environments for Gymnasium
Author: Hedwin Bonnavaud
Author-email: hbonnavaud@gmail.com
Requires-Python: >=3.8
Requires-Dist: gym>=0.26
Requires-Dist: gymnasium>=1.1
Requires-Dist: pygame
Requires-Dist: mujoco-py
Requires-Dist: numpy
Requires-Dist: opencv-python
Requires-Dist: matplotlib
Requires-Dist: scipy
Requires-Dist: scikit-image
Requires-Dist: imageio
Requires-Dist: networkx
Dynamic: author
Dynamic: author-email
Dynamic: requires-dist
Dynamic: requires-python
Dynamic: summary
